Metadata-Version: 2.0
Name: odoo9-addon-purchase-picking-state
Version: 9.0.1.0.0.99.dev16
Summary: Add the status of all the incoming picking in the purchase order
Home-page: http://akretion.com
Author: Akretion
Author-email: UNKNOWN
License: AGPL-3
Platform: UNKNOWN
Classifier: Programming Language :: Python
Classifier: Framework :: Odoo
Classifier: License :: OSI Approved :: GNU Affero General Public License v3
Requires-Python: ~=2.7
Requires-Dist: odoo (<9.1a,>=9.0a)
